LICENSE
README.md
asplode.py
setup.py
asplode.egg-info/PKG-INFO
asplode.egg-info/SOURCES.txt
asplode.egg-info/dependency_links.txt
asplode.egg-info/entry_points.txt
asplode.egg-info/not-zip-safe
asplode.egg-info/requires.txt
asplode.egg-info/top_level.txt